MANIFEST.in
README.md
requirements.txt
setup.py
django_yearmonth_widget/__init__.py
django_yearmonth_widget/admin.py
django_yearmonth_widget/apps.py
django_yearmonth_widget/models.py
django_yearmonth_widget/tests.py
django_yearmonth_widget/views.py
django_yearmonth_widget/widgets.py
django_yearmonth_widget.egg-info/PKG-INFO
django_yearmonth_widget.egg-info/SOURCES.txt
django_yearmonth_widget.egg-info/dependency_links.txt
django_yearmonth_widget.egg-info/not-zip-safe
django_yearmonth_widget.egg-info/requires.txt
django_yearmonth_widget.egg-info/top_level.txt
django_yearmonth_widget/migrations/__init__.py
django_yearmonth_widget/static/django-yearmonth-widget/js/django-yearmonth-widget.js
django_yearmonth_widget/static/django-yearmonth-widget/js/sprintf.min.js
django_yearmonth_widget/templates/django-yearmonth-widget/django-yearmonth-widget.html