Metadata-Version: 2.1
Name: django-yearmonth-widget
Version: 0.2.0
Summary: We only care about year and month for DateField, and always set the day to 1, it's a Django Widget allow you select the year and month. And now we support CharField backend.
Home-page: UNKNOWN
Author: zencore
Author-email: dobetter@zencore.cn
License: MIT
Keywords: django admin extentions,django yearmonth widget
Platform: UNKNOWN
Classifier: Development Status :: 5 - Production/Stable
Classifier: Intended Audience :: Developers
Classifier: Topic :: Software Development :: Libraries :: Python Modules
Classifier: License :: OSI Approved :: MIT License
Classifier: Programming Language :: Python :: 3
Classifier: Programming Language :: Python :: 3 :: Only
